[
  {
    "time": "PINGYELLOW",
    "colocacao": 1,
    "kills": 7
  },
  {
    "time": "Sons of Anarchy - Time B",
    "colocacao": 2,
    "kills": 0
  },
  {
    "time": "INESQUECIVEL",
    "colocacao": 3,
    "kills": 6
  },
  {
    "time": "STRAFE",
    "colocacao": 4,
    "kills": 1
  },
  {
    "time": "TÓXICOS",
    "colocacao": 5,
    "kills": 3
  },
  {
    "time": "Sons of Anarchy - Time A",
    "colocacao": 6,
    "kills": 0
  },
  {
    "time": "FURIA DO FURACÃO",
    "colocacao": 7,
    "kills": 0
  },
  {
    "time": "ASAS DO INFERNO",
    "colocacao": 8,
    "kills": 0
  }
]
